docs_src/conf.py
docs_src/generatePages.py
psychopy_eyetracker_tobii/__init__.py
psychopy_eyetracker_tobii/tobii/__init__.py
psychopy_eyetracker_tobii/tobii/calibration.py
psychopy_eyetracker_tobii/tobii/default_eyetracker.yaml
psychopy_eyetracker_tobii/tobii/eyetracker.py
psychopy_eyetracker_tobii/tobii/settings.py
psychopy_eyetracker_tobii/tobii/supported_config_settings.yaml
psychopy_eyetracker_tobii/tobii/tobiiwrapper.py
psychopy_eyetracker_tobii-0.0.3.dist-info/licenses/LICENSE
tests/__init__.py
tests/test_builder/__init__.py
tests/test_builder/test_eyetracker_backend.py
tests/test_coder/__init__.py
tobii/__init__.py
tobii/calibration.py
tobii/default_eyetracker.yaml
tobii/eyetracker.py
tobii/settings.py
tobii/supported_config_settings.yaml
tobii/tobiiwrapper.py
psychopy_eyetracker_tobii-0.0.3.dist-info/METADATA
psychopy_eyetracker_tobii-0.0.3.dist-info/WHEEL
psychopy_eyetracker_tobii-0.0.3.dist-info/entry_points.txt
psychopy_eyetracker_tobii-0.0.3.dist-info/top_level.txt
psychopy_eyetracker_tobii-0.0.3.dist-info/RECORD
